sorting_with_linus/__init__.py
sorting_with_linus/bubble_sort.py
sorting_with_linus/insertion_sort.py
sorting_with_linus/quick_sort.py
sorting_with_linus/selection_sort.py
sorting_with_linus-0.1.dist-info/METADATA
sorting_with_linus-0.1.dist-info/WHEEL
sorting_with_linus-0.1.dist-info/top_level.txt
sorting_with_linus-0.1.dist-info/RECORD
