Metadata-Version: 2.1
Name: sorting-with-linus
Version: 0.1
Summary: Just a few sorting algorithms, which you may find useful (or not).
Home-page: https://gitlab.propulsion-home.ch/linus-ritzmann/week-3/day-4
Author: Linus Ritzmann
Author-email: linus.ritzmann@gmail.com
License: MIT
Platform: UNKNOWN
Requires-Python: >=3.7
